space_console_game/animate_spaceship.py
space_console_game/app.py
space_console_game/app_helpers.py
space_console_game/curses_tools.py
space_console_game/fire_animation.py
space_console_game/frames/rocket_frame_1.txt 
space_console_game/frames/rocket_frame_2.txt 
space_console_game-0.1.3.dist-info/entry_points.txt
space_console_game-0.1.3.dist-info/LICENSE
space_console_game-0.1.3.dist-info/WHEEL
space_console_game-0.1.3.dist-info/METADATA
space_console_game-0.1.3.dist-info/RECORD
